wegene/APIException.py
wegene/APIHelper.py
wegene/Configuration.py
wegene/__init__.py
wegene/Controllers/Allele.py
wegene/Controllers/Ancestry.py
wegene/Controllers/Athletigen.py
wegene/Controllers/Demographics.py
wegene/Controllers/Haplogroups.py
wegene/Controllers/Health.py
wegene/Controllers/Psychology.py
wegene/Controllers/Risk.py
wegene/Controllers/Skin.py
wegene/Controllers/WeGeneUser.py
wegene/Controllers/__init__.py
wegene/Models/AncestryArea.py
wegene/Models/AncestryBlock.py
wegene/Models/AncestryComposition.py
wegene/Models/Demographic.py
wegene/Models/GenotypeModel.py
wegene/Models/GenotypesModel.py
wegene/Models/Haplogroup.py
wegene/Models/Profile.py
wegene/Models/Report.py
wegene/Models/User.py
wegene/Models/__init__.py
wegene-0.1.4.dist-info/DESCRIPTION.rst
wegene-0.1.4.dist-info/METADATA
wegene-0.1.4.dist-info/RECORD
wegene-0.1.4.dist-info/WHEEL
wegene-0.1.4.dist-info/metadata.json
wegene-0.1.4.dist-info/top_level.txt
