Metadata-Version: 2.0
Name: wegene
Version: 0.1.4
Summary: WeGene SDK for Python
Home-page: https://github.com/xraywu/wegene-python-sdk
Author: Eddie Wu
Author-email: xrayxiaoli@gmail.com
License: MIT
Platform: UNKNOWN
Classifier: Programming Language :: Python
Classifier: Programming Language :: Python :: 2.7
Classifier: Programming Language :: Python :: 3.6
Requires-Dist: requests (==2.21.0)
Requires-Dist: jsonpickle (==0.7.1)
